{
  "collection_name": "schema_chunks",
  "enable_dynamic_field": false,
  "fields": [
    {
      "auto_id": false,
      "default_value": null,
      "dim": null,
      "dtype": "varchar",
      "element_type": null,
      "is_primary": true,
      "max_capacity": null,
      "max_length": 64,
      "name": "id",
      "nullable": false
    },
    {
      "auto_id": false,
      "default_value": null,
      "dim": null,
      "dtype": "varchar",
      "element_type": null,
      "is_primary": false,
      "max_capacity": null,
      "max_length": 256,
      "name": "database_name",
      "nullable": false
    },
    {
      "auto_id": false,
      "default_value": null,
      "dim": null,
      "dtype": "varchar",
      "element_type": null,
      "is_primary": false,
      "max_capacity": null,
      "max_length": 256,
      "name": "table_name",
      "nullable": false
    },
    {
      "auto_id": false,
      "default_value": null,
      "dim": null,
      "dtype": "varchar",
      "element_type": null,
      "is_primary": false,
      "max_capacity": null,
      "max_length": 10000,
      "name": "embedding_text",
      "nullable": false
    },
    {
      "auto_id": false,
      "default_value": null,
      "dim": null,
      "dtype": "varchar",
      "element_type": null,
      "is_primary": false,
      "max_capacity": null,
      "max_length": 65535,
      "name": "raw_ddl",
      "nullable": false
    },
    {
      "auto_id": false,
      "default_value": null,
      "dim": null,
      "dtype": "varchar",
      "element_type": null,
      "is_primary": false,
      "max_capacity": null,
      "max_length": 512,
      "name": "source_file",
      "nullable": false
    },
    {
      "auto_id": false,
      "default_value": null,
      "dim": 768,
      "dtype": "float_vector",
      "element_type": null,
      "is_primary": false,
      "max_capacity": null,
      "max_length": null,
      "name": "embedding",
      "nullable": false
    }
  ],
  "schema_format_version": 2,
  "version": 1
}